jeanmemory/__init__.py
jeanmemory/auth.py
jeanmemory/cli.py
jeanmemory/client.py
jeanmemory/mcp.py
jeanmemory/models.py
jeanmemory-2.0.8.dist-info/METADATA
jeanmemory-2.0.8.dist-info/WHEEL
jeanmemory-2.0.8.dist-info/top_level.txt
jeanmemory-2.0.8.dist-info/RECORD
