Metadata-Version: 2.1
Name: jeanmemory
Version: 2.0.8
Summary: Python SDK for Jean Memory - Add long-term memory to your Python agents and backend services
Home-page: https://github.com/jean-technologies/jean-memory
Author: Jean Memory
Author-email: support@jeanmemory.com
License: UNKNOWN
Project-URL: Bug Tracker, https://github.com/jean-technologies/jean-memory/issues
Project-URL: Documentation, https://jeanmemory.com/docs
Project-URL: Homepage, https://jeanmemory.com
Keywords: jean-memory ai chatbot personalization sdk
Platform: UNKNOWN
Classifier: Development Status :: 3 - Alpha
Classifier: Intended Audience :: Developers
Classifier: License :: OSI Approved :: MIT License
Classifier: Operating System :: OS Independent
Classifier: Programming Language :: Python :: 3
Classifier: Programming Language :: Python :: 3.8
Classifier: Programming Language :: Python :: 3.9
Classifier: Programming Language :: Python :: 3.10
Classifier: Programming Language :: Python :: 3.11
Classifier: Programming Language :: Python :: 3.12
Classifier: Programming Language :: Python :: 3.13
Classifier: Topic :: Software Development :: Libraries :: Python Modules
Classifier: Topic :: Scientific/Engineering :: Artificial Intelligence
Requires-Python: >=3.8
Requires-Dist: requests>=2.25.0
Provides-Extra: openai
Requires-Dist: openai>=1.0.0; extra == "openai"
